immosheets/__init__.py
immosheets/area.py
immosheets/location.py
immosheets/range.py
immosheets/real_estate.py
immosheets/real_estate_service.py
immosheets/reporting_service.py
immosheets/settings.py
immosheets/target.py
immosheets/era/__init__.py
immosheets/era/era_location.py
immosheets/era/era_search_query.py
immosheets/era/era_service.py
immosheets/era/postal_code.py
immosheets/era/utils.py
immosheets/google_sheets/__init__.py
immosheets/google_sheets/google_spreadsheets_service.py
immosheets/orpi/__init__.py
immosheets/orpi/orpi_search_query.py
immosheets/orpi/orpi_service.py
immosheets/orpi/orpi_transaction_type.py
immosheets/seloger/__init__.py
immosheets/seloger/seloger_real_estate_filter.py
immosheets/seloger/seloger_real_estate_type.py
immosheets/seloger/seloger_search_query.py
immosheets/seloger/seloger_service.py
immosheets/seloger/seloger_transaction_type.py
immosheets-1.2.2.dist-info/licenses/LICENSE
immosheets-1.2.2.dist-info/METADATA
immosheets-1.2.2.dist-info/WHEEL
immosheets-1.2.2.dist-info/top_level.txt
immosheets-1.2.2.dist-info/RECORD
