Metadata-Version: 2.4
Name: immosheets
Version: 1.2.2
Summary: Tired of searching with your mouse ? Let's automate the process.
Home-page: https://github.com/arthuRHD/immosheets
Author: Arthur RICHARD
Author-email: arthur.richard@protonmail.com
Classifier: Programming Language :: Python :: 3
Classifier: License :: OSI Approved :: MIT License
Classifier: Operating System :: OS Independent
Requires-Python: >=3.10
License-File: LICENSE
Requires-Dist: requests==2.32.2
Requires-Dist: google-api-core==2.14.0
Requires-Dist: google-api-python-client==2.122.0
Requires-Dist: google-auth==2.23.4
Requires-Dist: google-auth-httplib2==0.2.0
Requires-Dist: google-auth-oauthlib==1.2.0
Requires-Dist: Deprecated==1.2.14
Dynamic: author
Dynamic: author-email
Dynamic: classifier
Dynamic: description
Dynamic: description-content-type
Dynamic: home-page
Dynamic: license-file
Dynamic: requires-dist
Dynamic: requires-python
Dynamic: summary
